lotgi/__init__.py
lotgi/__main__.py
lotgi/_openai.py
lotgi/convert_to_seconds.py
lotgi/logging.py
lotgi/rest_client.py
lotgi/tokens.py
lotgi/asyncio/rest_client.py
lotgi/models/rest.py
tests/test_basic.py
tests/test_convert_to_seconds.py
lotgi-0.0.9.dist-info/METADATA
lotgi-0.0.9.dist-info/WHEEL
lotgi-0.0.9.dist-info/entry_points.txt
lotgi-0.0.9.dist-info/top_level.txt
lotgi-0.0.9.dist-info/RECORD
